plot_magic/__init__.py
plot_magic/viz.py
PlotMagic-0.3.dist-info/METADATA
PlotMagic-0.3.dist-info/WHEEL
PlotMagic-0.3.dist-info/top_level.txt
PlotMagic-0.3.dist-info/RECORD
