Metadata-Version: 2.1
Name: PlotMagic
Version: 0.3
Summary: A Python package for easy-to-use advanced visualizations
Author: Aditya Srivastav
Author-email: adityathestar2006@gmail.com
Classifier: Programming Language :: Python :: 3
Classifier: Programming Language :: Python :: 3.6
Classifier: Programming Language :: Python :: 3.7
Classifier: Programming Language :: Python :: 3.8
Classifier: Programming Language :: Python :: 3.9
Classifier: License :: OSI Approved :: Apache Software License
Classifier: Operating System :: OS Independent
Requires-Python: >=3.6
Requires-Dist: matplotlib
Requires-Dist: seaborn
Requires-Dist: numpy
Requires-Dist: pandas
